{"anggur": 0, "apel": 1, "ayam": 2, "bawang": 3, "bayam": 4, "belimbing": 5, "bombay": 6, "brokoli": 7, "buah_bit": 8, "cabai_rawit": 9, "delima": 10, "ikan": 11, "jagung": 12, "jagung_manis": 13, "jahe": 14, "jalepeno": 15, "jeruk": 16, "kacang_kedelai": 17, "kacang_polong": 18, "kangkung": 19, "kapsikum": 20, "kelapa": 21, "kembang_kol": 22, "kentang": 23, "kiwi": 24, "kubis": 25, "lemon": 26, "lobak": 27, "mangga": 28, "nanas": 29, "paprika": 30, "pare": 31, "pir": 32, "pisang": 33, "pokcoy": 34, "red_paprika": 35, "sapi": 36, "selada": 37, "semangka": 38, "singkong": 39, "tahu": 40, "telur": 41, "tempe": 42, "terong": 43, "timun": 44, "tomat": 45, "ubi_jalar": 46, "ubi_lobak": 47, "udang": 48, "wortel": 49}